{"v":"5.6.5","fr":100,"ip":0,"op":399,"w":530,"h":84,"nm":"音乐小耳朵","ddd":0,"assets":[{"id":"comp_0","layers":[{"ddd":0,"ind":1,"ty":4,"nm":"Shape Layer 4","sr":1,"ks":{"o":{"a":1,"k":[{"i":{"x":[0.667],"y":[1]},"o":{"x":[0.333],"y":[0]},"t":8,"s":[0]},{"i":{"x":[0.667],"y":[1]},"o":{"x":[0.333],"y":[0]},"t":20,"s":[100]},{"i":{"x":[0.667],"y":[1]},"o":{"x":[0.333],"y":[0]},"t":149.945,"s":[100]},{"t":161.9453125,"s":[0]}],"ix":11},"r":{"a":0,"k":0,"ix":10},"p":{"a":1,"k":[{"i":{"x":0.6,"y":1},"o":{"x":0.32,"y":0.94},"t":40,"s":[439.9,41.507,0],"to":[8.417,0,0],"ti":[-8.417,0,0]},{"i":{"x":0.6,"y":0.6},"o":{"x":0.32,"y":0.32},"t":78,"s":[490.4,41.507,0],"to":[0,0,0],"ti":[0,0,0]},{"i":{"x":0.6,"y":1},"o":{"x":0.32,"y":0.94},"t":108,"s":[490.4,41.507,0],"to":[-8.417,0,0],"ti":[8.417,0,0]},{"t":148,"s":[439.9,41.507,0]}],"ix":2},"a":{"a":0,"k":[-320.922,454.078,0],"ix":1},"s":{"a":1,"k":[{"i":{"x":[0.667,0.667,0.667],"y":[1,1,1]},"o":{"x":[0.333,0.333,0.333],"y":[0,0,0]},"t":8,"s":[100,100,100]},{"i":{"x":[0.667,0.667,0.667],"y":[1,1,1]},"o":{"x":[0.333,0.333,0.333],"y":[0,0,0]},"t":20,"s":[70,70,100]},{"i":{"x":[0.667,0.667,0.667],"y":[1,1,1]},"o":{"x":[0.333,0.333,0.333],"y":[0,0,0]},"t":150,"s":[70.002,70,100]},{"t":162,"s":[100,100,100]}],"ix":6}},"ao":0,"shapes":[{"ty":"gr","it":[{"d":1,"ty":"el","s":{"a":0,"k":[46.156,46.156],"ix":2},"p":{"a":0,"k":[0,0],"ix":3},"nm":"Ellipse Path 1","mn":"ADBE Vector Shape - Ellipse","hd":false},{"ty":"st","c":{"a":0,"k":[1,1,1,1],"ix":3},"o":{"a":0,"k":100,"ix":4},"w":{"a":0,"k":2,"ix":5},"lc":1,"lj":1,"ml":4,"bm":0,"nm":"Stroke 1","mn":"ADBE Vector Graphic - Stroke","hd":false},{"ty":"fl","c":{"a":0,"k":[0.29214155674,0.861811578274,1,1],"ix":4},"o":{"a":0,"k":50,"ix":5},"r":1,"bm":0,"nm":"Fill 1","mn":"ADBE Vector Graphic - Fill","hd":false},{"ty":"tr","p":{"a":0,"k":[-320.922,454.078],"ix":2},"a":{"a":0,"k":[0,0],"ix":1},"s":{"a":0,"k":[100,100],"ix":3},"r":{"a":0,"k":0,"ix":6},"o":{"a":0,"k":100,"ix":7},"sk":{"a":0,"k":0,"ix":4},"sa":{"a":0,"k":0,"ix":5},"nm":"变换"}],"nm":"Ellipse 1","np":3,"cix":2,"bm":0,"ix":1,"mn":"ADBE Vector Group","hd":false}],"ip":0,"op":2000,"st":0,"bm":0},{"ddd":0,"ind":2,"ty":4,"nm":"中间","sr":1,"ks":{"o":{"a":0,"k":100,"ix":11},"r":{"a":0,"k":0,"ix":10},"p":{"a":1,"k":[{"i":{"x":0.6,"y":1},"o":{"x":0.32,"y":0.965},"t":220,"s":[136,42,0],"to":[6.333,0,0],"ti":[-6.333,0,0]},{"i":{"x":0.6,"y":0.6},"o":{"x":0.32,"y":0.32},"t":258,"s":[174,42,0],"to":[0,0,0],"ti":[0,0,0]},{"i":{"x":0.6,"y":1},"o":{"x":0.32,"y":0.94},"t":288,"s":[174,42,0],"to":[-6.5,0,0],"ti":[6.5,0,0]},{"t":326,"s":[135,42,0]}],"ix":2},"a":{"a":0,"k":[-130.5,0,0],"ix":1},"s":{"a":1,"k":[{"i":{"x":[0.6,0.6,0.6],"y":[1,1,1]},"o":{"x":[0.32,0.32,0.32],"y":[0.94,0,0]},"t":40,"s":[100,116.7,100]},{"i":{"x":[0.6,0.6,0.6],"y":[1,1,1]},"o":{"x":[0.32,0.32,0.32],"y":[0,0,0]},"t":78,"s":[120,116.7,100]},{"i":{"x":[0.6,0.6,0.6],"y":[1,1,1]},"o":{"x":[0.32,0.32,0.32],"y":[0.94,0,0]},"t":108,"s":[120,116.7,100]},{"t":148,"s":[100,116.7,100]}],"ix":6}},"ao":0,"shapes":[{"ty":"gr","it":[{"ind":0,"ty":"sh","ix":1,"ks":{"a":0,"k":{"i":[[0,0],[0,0],[0,0],[0,0]],"o":[[0,0],[0,0],[0,0],[0,0]],"v":[[130.5,-36],[130.5,36],[-130.5,36],[-130.5,-36]],"c":true},"ix":2},"nm":"路径 1","mn":"ADBE Vector Shape - Group","hd":false},{"ind":1,"ty":"sh","ix":2,"ks":{"a":0,"k":{"i":[[0,0],[0,0],[0,0],[0,0]],"o":[[0,0],[0,0],[0,0],[0,0]],"v":[[124.5,-30],[-124.5,-30],[-124.5,30],[124.5,30]],"c":true},"ix":2},"nm":"路径 2","mn":"ADBE Vector Shape - Group","hd":false},{"ty":"mm","mm":1,"nm":"合并路径 1","mn":"ADBE Vector Filter - Merge","hd":false},{"ty":"fl","c":{"a":0,"k":[1,1,1,1],"ix":4},"o":{"a":0,"k":100,"ix":5},"r":1,"bm":0,"nm":"填充 1","mn":"ADBE Vector Graphic - Fill","hd":false},{"ty":"tr","p":{"a":0,"k":[0,0],"ix":2},"a":{"a":0,"k":[0,0],"ix":1},"s":{"a":0,"k":[100,100],"ix":3},"r":{"a":0,"k":0,"ix":6},"o":{"a":0,"k":100,"ix":7},"sk":{"a":0,"k":0,"ix":4},"sa":{"a":0,"k":0,"ix":5},"nm":"变换"}],"nm":"蒙版","np":4,"cix":2,"bm":0,"ix":1,"mn":"ADBE Vector Group","hd":false}],"ip":0,"op":6000,"st":0,"bm":0},{"ddd":0,"ind":3,"ty":4,"nm":"矩形","parent":4,"sr":1,"ks":{"o":{"a":0,"k":100,"ix":11},"r":{"a":0,"k":0,"ix":10},"p":{"a":0,"k":[0,0,0],"ix":2},"a":{"a":0,"k":[0,0,0],"ix":1},"s":{"a":0,"k":[100,85.587,100],"ix":6}},"ao":0,"shapes":[{"ty":"gr","it":[{"ty":"rc","d":1,"s":{"a":0,"k":[6,24],"ix":2},"p":{"a":0,"k":[0,0],"ix":3},"r":{"a":0,"k":6,"ix":4},"nm":"矩形路径 1","mn":"ADBE Vector Shape - Rect","hd":false},{"ty":"gf","o":{"a":0,"k":100,"ix":10},"r":1,"bm":0,"g":{"p":5,"k":{"a":0,"k":[0,0.312,0.578,1,0.196,0.258,0.72,1,0.392,0.204,0.863,1,0.696,0.59,0.776,0.924,1,0.976,0.69,0.847],"ix":9}},"s":{"a":0,"k":[-1.815,-11.631],"ix":5},"e":{"a":0,"k":[2.441,11.446],"ix":6},"t":1,"nm":"gradual","mn":"ADBE Vector Graphic - G-Fill","hd":false},{"ty":"tr","p":{"a":0,"k":[0,0],"ix":2},"a":{"a":0,"k":[0,0],"ix":1},"s":{"a":0,"k":[100,100],"ix":3},"r":{"a":0,"k":0,"ix":6},"o":{"a":0,"k":100,"ix":7},"sk":{"a":0,"k":0,"ix":4},"sa":{"a":0,"k":0,"ix":5},"nm":"变换"}],"nm":"矩形","np":2,"cix":2,"bm":0,"ix":1,"mn":"ADBE Vector Group","hd":false}],"ip":0,"op":6000,"st":0,"bm":0},{"ddd":0,"ind":4,"ty":4,"nm":"右边手柄","sr":1,"ks":{"o":{"a":0,"k":100,"ix":11},"r":{"a":0,"k":0,"ix":10},"p":{"a":1,"k":[{"i":{"x":0.6,"y":1},"o":{"x":0.32,"y":0.932},"t":40,"s":[417,42,0],"to":[8.75,0,0],"ti":[-8.75,0,0]},{"i":{"x":0.6,"y":0.6},"o":{"x":0.32,"y":0.32},"t":78,"s":[469.5,42,0],"to":[0,0,0],"ti":[0,0,0]},{"i":{"x":0.6,"y":1},"o":{"x":0.32,"y":0.94},"t":108,"s":[469.5,42,0],"to":[-8.75,0,0],"ti":[8.75,0,0]},{"i":{"x":0.667,"y":0.667},"o":{"x":0.167,"y":0.167},"t":148,"s":[417,42,0],"to":[0,0,0],"ti":[0,0,0]},{"i":{"x":0.6,"y":1},"o":{"x":0.32,"y":0.94},"t":220,"s":[417,42,0],"to":[6.542,0,0],"ti":[-6.542,0,0]},{"i":{"x":0.6,"y":0.6},"o":{"x":0.32,"y":0.32},"t":258,"s":[456.25,42,0],"to":[0,0,0],"ti":[0,0,0]},{"i":{"x":0.6,"y":1},"o":{"x":0.32,"y":0.94},"t":288,"s":[456.25,42,0],"to":[-6.542,0,0],"ti":[6.542,0,0]},{"t":326,"s":[417,42,0]}],"ix":2},"a":{"a":0,"k":[0,0,0],"ix":1},"s":{"a":0,"k":[100,116.84,100],"ix":6}},"ao":0,"shapes":[{"ty":"gr","it":[{"ind":0,"ty":"sh","ix":1,"ks":{"a":0,"k":{"i":[[6.63,0],[0,0],[0,0],[0,0],[0,-6.63],[0,0]],"o":[[0,0],[0,0],[0,0],[6.63,0],[0,0],[0,6.63]],"v":[[15,36],[-27,36],[-27,-36],[15,-36],[27,-24],[27,24]],"c":true},"ix":2},"nm":"路径 1","mn":"ADBE Vector Shape - Group","hd":false},{"ty":"fl","c":{"a":0,"k":[1,1,1,1],"ix":4},"o":{"a":0,"k":100,"ix":5},"r":1,"bm":0,"nm":"填充 1","mn":"ADBE Vector Graphic - Fill","hd":false},{"ty":"tr","p":{"a":0,"k":[0,0],"ix":2},"a":{"a":0,"k":[0,0],"ix":1},"s":{"a":0,"k":[100,100],"ix":3},"r":{"a":0,"k":0,"ix":6},"o":{"a":0,"k":100,"ix":7},"sk":{"a":0,"k":0,"ix":4},"sa":{"a":0,"k":0,"ix":5},"nm":"变换"}],"nm":"矩形","np":2,"cix":2,"bm":0,"ix":1,"mn":"ADBE Vector Group","hd":false}],"ip":0,"op":6000,"st":0,"bm":0},{"ddd":0,"ind":5,"ty":4,"nm":"矩形","parent":6,"sr":1,"ks":{"o":{"a":0,"k":100,"ix":11},"r":{"a":0,"k":0,"ix":10},"p":{"a":0,"k":[0,0,0],"ix":2},"a":{"a":0,"k":[0,0,0],"ix":1},"s":{"a":0,"k":[100,85.714,100],"ix":6}},"ao":0,"shapes":[{"ty":"gr","it":[{"ty":"rc","d":1,"s":{"a":0,"k":[6,24],"ix":2},"p":{"a":0,"k":[0,0],"ix":3},"r":{"a":0,"k":6,"ix":4},"nm":"矩形路径 1","mn":"ADBE Vector Shape - Rect","hd":false},{"ty":"gf","o":{"a":0,"k":100,"ix":10},"r":1,"bm":0,"g":{"p":5,"k":{"a":0,"k":[0,0.312,0.578,1,0.196,0.258,0.72,1,0.392,0.204,0.863,1,0.696,0.59,0.776,0.924,1,0.976,0.69,0.847],"ix":9}},"s":{"a":0,"k":[-1.953,-11.424],"ix":5},"e":{"a":0,"k":[2.01,11.738],"ix":6},"t":1,"nm":"gradual","mn":"ADBE Vector Graphic - G-Fill","hd":false},{"ty":"tr","p":{"a":0,"k":[0,0],"ix":2},"a":{"a":0,"k":[0,0],"ix":1},"s":{"a":0,"k":[100,100],"ix":3},"r":{"a":0,"k":0,"ix":6},"o":{"a":0,"k":100,"ix":7},"sk":{"a":0,"k":0,"ix":4},"sa":{"a":0,"k":0,"ix":5},"nm":"变换"}],"nm":"矩形","np":2,"cix":2,"bm":0,"ix":1,"mn":"ADBE Vector Group","hd":false}],"ip":0,"op":6000,"st":0,"bm":0},{"ddd":0,"ind":6,"ty":4,"nm":"左边手柄","sr":1,"ks":{"o":{"a":0,"k":100,"ix":11},"r":{"a":0,"k":0,"ix":10},"p":{"a":1,"k":[{"i":{"x":0.6,"y":1},"o":{"x":0.32,"y":0.965},"t":220,"s":[115,42,0],"to":[6.292,0,0],"ti":[-6.292,0,0]},{"i":{"x":0.6,"y":0.6},"o":{"x":0.32,"y":0.32},"t":258,"s":[152.75,42,0],"to":[0,0,0],"ti":[0,0,0]},{"i":{"x":0.6,"y":1},"o":{"x":0.32,"y":0.965},"t":288,"s":[152.75,42,0],"to":[-6.292,0,0],"ti":[6.292,0,0]},{"t":326,"s":[115,42,0]}],"ix":2},"a":{"a":0,"k":[0,0,0],"ix":1},"s":{"a":0,"k":[100,116.667,100],"ix":6}},"ao":0,"shapes":[{"ty":"gr","it":[{"ind":0,"ty":"sh","ix":1,"ks":{"a":0,"k":{"i":[[-6.63,0],[0,0],[0,0],[0,0],[0,6.63],[0,0]],"o":[[0,0],[0,0],[0,0],[-6.63,0],[0,0],[0,-6.63]],"v":[[-15,-36],[27,-36],[27,36],[-15,36],[-27,24],[-27,-24]],"c":true},"ix":2},"nm":"路径 1","mn":"ADBE Vector Shape - Group","hd":false},{"ty":"fl","c":{"a":0,"k":[1,1,1,1],"ix":4},"o":{"a":0,"k":100,"ix":5},"r":1,"bm":0,"nm":"填充 1","mn":"ADBE Vector Graphic - Fill","hd":false},{"ty":"tr","p":{"a":0,"k":[0,0],"ix":2},"a":{"a":0,"k":[0,0],"ix":1},"s":{"a":0,"k":[100,100],"ix":3},"r":{"a":0,"k":0,"ix":6},"o":{"a":0,"k":100,"ix":7},"sk":{"a":0,"k":0,"ix":4},"sa":{"a":0,"k":0,"ix":5},"nm":"变换"}],"nm":"矩形","np":2,"cix":2,"bm":0,"ix":1,"mn":"ADBE Vector Group","hd":false}],"ip":0,"op":6000,"st":0,"bm":0}]}],"layers":[{"ddd":0,"ind":1,"ty":4,"nm":"Shape Layer 5","sr":1,"ks":{"o":{"a":1,"k":[{"i":{"x":[0.667],"y":[1]},"o":{"x":[0.333],"y":[0]},"t":200,"s":[0]},{"i":{"x":[0.667],"y":[1]},"o":{"x":[0.333],"y":[0]},"t":212,"s":[100]},{"i":{"x":[0.667],"y":[1]},"o":{"x":[0.333],"y":[0]},"t":341.945,"s":[100]},{"t":353.9453125,"s":[0]}],"ix":11},"r":{"a":0,"k":0,"ix":10},"p":{"a":1,"k":[{"i":{"x":0.6,"y":1},"o":{"x":0.32,"y":0.94},"t":220,"s":[265.5,41.578,0],"to":[6.5,0,0],"ti":[-6.5,0,0]},{"i":{"x":0.6,"y":0.6},"o":{"x":0.32,"y":0.32},"t":258,"s":[304.5,41.578,0],"to":[0,0,0],"ti":[0,0,0]},{"i":{"x":0.6,"y":1},"o":{"x":0.32,"y":0.94},"t":288,"s":[304.5,41.578,0],"to":[-6.5,0,0],"ti":[6.5,0,0]},{"t":326,"s":[265.5,41.578,0]}],"ix":2},"a":{"a":0,"k":[-320.922,454.078,0],"ix":1},"s":{"a":1,"k":[{"i":{"x":[0.667,0.667,0.667],"y":[1,1,1]},"o":{"x":[0.333,0.333,0.333],"y":[0,0,0]},"t":200,"s":[100,100,100]},{"i":{"x":[0.667,0.667,0.667],"y":[1,1,1]},"o":{"x":[0.333,0.333,0.333],"y":[0,0,0]},"t":212,"s":[70,70,100]},{"i":{"x":[0.667,0.667,0.667],"y":[1,1,1]},"o":{"x":[0.333,0.333,0.333],"y":[0,0,0]},"t":341.945,"s":[70,70,100]},{"t":353.9453125,"s":[100,100,100]}],"ix":6}},"ao":0,"shapes":[{"ty":"gr","it":[{"d":1,"ty":"el","s":{"a":0,"k":[46.156,46.156],"ix":2},"p":{"a":0,"k":[0,0],"ix":3},"nm":"Ellipse Path 1","mn":"ADBE Vector Shape - Ellipse","hd":false},{"ty":"st","c":{"a":0,"k":[1,1,1,1],"ix":3},"o":{"a":0,"k":100,"ix":4},"w":{"a":0,"k":2,"ix":5},"lc":1,"lj":1,"ml":4,"bm":0,"nm":"Stroke 1","mn":"ADBE Vector Graphic - Stroke","hd":false},{"ty":"fl","c":{"a":0,"k":[1,1,1,1],"ix":4},"o":{"a":0,"k":50,"ix":5},"r":1,"bm":0,"nm":"Fill 1","mn":"ADBE Vector Graphic - Fill","hd":false},{"ty":"tr","p":{"a":0,"k":[-320.922,454.078],"ix":2},"a":{"a":0,"k":[0,0],"ix":1},"s":{"a":0,"k":[100,100],"ix":3},"r":{"a":0,"k":0,"ix":6},"o":{"a":0,"k":100,"ix":7},"sk":{"a":0,"k":0,"ix":4},"sa":{"a":0,"k":0,"ix":5},"nm":"变换"}],"nm":"Ellipse 1","np":3,"cix":2,"bm":0,"ix":1,"mn":"ADBE Vector Group","hd":false}],"ip":0,"op":2000,"st":0,"bm":0},{"ddd":0,"ind":3,"ty":0,"nm":"音乐小耳朵内置","refId":"comp_0","sr":1,"ks":{"o":{"a":1,"k":[{"i":{"x":[0.833],"y":[0.833]},"o":{"x":[0.167],"y":[0.167]},"t":200,"s":[100]},{"i":{"x":[0.833],"y":[0.833]},"o":{"x":[0.167],"y":[0.167]},"t":212,"s":[70]},{"i":{"x":[0.833],"y":[0.833]},"o":{"x":[0.167],"y":[0.167]},"t":342,"s":[70]},{"t":354,"s":[100]}],"ix":11},"r":{"a":0,"k":0,"ix":10},"p":{"a":0,"k":[265,42,0],"ix":2},"a":{"a":0,"k":[265,42,0],"ix":1},"s":{"a":0,"k":[100,100,100],"ix":6}},"ao":0,"w":530,"h":84,"ip":0,"op":6000,"st":0,"bm":0}],"markers":[]}
